mai_bias/__init__.py
mai_bias/app.py
mai_bias/app_unsafe.py
mai_bias/cli.py
mai_bias/backend/__init__.py
mai_bias/backend/catalogue_loaders.py
mai_bias/backend/loaders.py
mai_bias/backend/registry.py
mai_bias/catalogue/__init__.py
mai_bias/catalogue/dataset_loaders/__init__.py
mai_bias/catalogue/dataset_loaders/auto_csv.py
mai_bias/catalogue/dataset_loaders/custom_csv.py
mai_bias/catalogue/dataset_loaders/data_any.py
mai_bias/catalogue/dataset_loaders/data_csv_rankings.py
mai_bias/catalogue/dataset_loaders/data_researchers.py
mai_bias/catalogue/dataset_loaders/free_text.py
mai_bias/catalogue/dataset_loaders/graph.py
mai_bias/catalogue/dataset_loaders/image_pairs.py
mai_bias/catalogue/dataset_loaders/images.py
mai_bias/catalogue/dataset_loaders/uci_csv.py
mai_bias/catalogue/metrics/__init__.py
mai_bias/catalogue/metrics/aif360_metrics.py
mai_bias/catalogue/metrics/augmentation_report.py
mai_bias/catalogue/metrics/bias_scan.py
mai_bias/catalogue/metrics/croissant.py
mai_bias/catalogue/metrics/image_bias_analysis.py
mai_bias/catalogue/metrics/interactive_report.py
mai_bias/catalogue/metrics/model_card.py
mai_bias/catalogue/metrics/multi_objective_report.py
mai_bias/catalogue/metrics/networks_layouts.py
mai_bias/catalogue/metrics/optimal_transport.py
mai_bias/catalogue/metrics/ranking_fairness.py
mai_bias/catalogue/metrics/self_critic.py
mai_bias/catalogue/metrics/sklearn_audit.py
mai_bias/catalogue/metrics/sklearn_visual_analysis.py
mai_bias/catalogue/metrics/specific_concerns.py
mai_bias/catalogue/metrics/text_dbias.py
mai_bias/catalogue/metrics/viz_fairness_plots.py
mai_bias/catalogue/metrics/viz_fairness_report.py
mai_bias/catalogue/metrics/xai_analysis.py
mai_bias/catalogue/metrics/xai_analysis_embeddings.py
mai_bias/catalogue/model_loaders/__init__.py
mai_bias/catalogue/model_loaders/compute_rankings.py
mai_bias/catalogue/model_loaders/compute_researcher_ranking.py
mai_bias/catalogue/model_loaders/fair_node_ranking.py
mai_bias-0.2.25.dist-info/licenses/LICENSE
mai_bias-0.2.25.dist-info/METADATA
mai_bias-0.2.25.dist-info/WHEEL
mai_bias-0.2.25.dist-info/top_level.txt
mai_bias-0.2.25.dist-info/RECORD
