Metadata-Version: 2.4
Name: MAI-Bias
Version: 0.2.25
Summary: Desktop app version of the MAI-Bias toolkit.
Home-page: https://github.com/mammoth-eu/mammoth-commons
Author: Emmanouil (Manios) Krasanakis
Author-email: maniospas@hotmail.com
Classifier: Programming Language :: Python :: 3
Classifier: Operating System :: OS Independent
Requires-Python: >=3.11
License-File: LICENSE
Requires-Dist: mammoth-commons[deployment]>=0.1.20
Requires-Dist: fairbench
Requires-Dist: pandas
Requires-Dist: PyYAML
Requires-Dist: kfp===2.11.0
Requires-Dist: onnx
Requires-Dist: onnxruntime
Requires-Dist: docker
Requires-Dist: PySide6
Requires-Dist: html2text
Requires-Dist: readchar
Requires-Dist: rich
Requires-Dist: click
Dynamic: author
Dynamic: author-email
Dynamic: classifier
Dynamic: description
Dynamic: description-content-type
Dynamic: home-page
Dynamic: license-file
Dynamic: requires-dist
Dynamic: requires-python
Dynamic: summary
